[
  {
    "name": "child",
    "path": "/child",
    "component": "C:\\\\Users\\\\acer\\\\Desktop\\\\allfiles\\\\palExchange\\\\frontend\\\\pages\\\\child.vue",
    "chunkName": "pages/child",
    "_name": "_6ae5d590"
  },
  {
    "name": "dashboard",
    "path": "/dashboard",
    "component": "C:\\\\Users\\\\acer\\\\Desktop\\\\allfiles\\\\palExchange\\\\frontend\\\\pages\\\\dashboard\\\\index.vue",
    "chunkName": "pages/dashboard/index",
    "_name": "_6166fc5c"
  },
  {
    "name": "inspire",
    "path": "/inspire",
    "component": "C:\\\\Users\\\\acer\\\\Desktop\\\\allfiles\\\\palExchange\\\\frontend\\\\pages\\\\inspire.vue",
    "chunkName": "pages/inspire",
    "_name": "_785bb2f6"
  },
  {
    "name": "parent",
    "path": "/parent",
    "component": "C:\\\\Users\\\\acer\\\\Desktop\\\\allfiles\\\\palExchange\\\\frontend\\\\pages\\\\parent.vue",
    "chunkName": "pages/parent",
    "_name": "_2a5a6b3e"
  },
  {
    "name": "test",
    "path": "/test",
    "component": "C:\\\\Users\\\\acer\\\\Desktop\\\\allfiles\\\\palExchange\\\\frontend\\\\pages\\\\test.vue",
    "chunkName": "pages/test",
    "_name": "_6ae2fbb4"
  },
  {
    "name": "auth-login",
    "path": "/auth/login",
    "component": "C:\\\\Users\\\\acer\\\\Desktop\\\\allfiles\\\\palExchange\\\\frontend\\\\pages\\\\auth\\\\login.vue",
    "chunkName": "pages/auth/login",
    "_name": "_6ea4dbdd"
  },
  {
    "name": "auth-register",
    "path": "/auth/register",
    "component": "C:\\\\Users\\\\acer\\\\Desktop\\\\allfiles\\\\palExchange\\\\frontend\\\\pages\\\\auth\\\\register.vue",
    "chunkName": "pages/auth/register",
    "_name": "_fdc25842"
  },
  {
    "name": "dashboard-beneficiaries",
    "path": "/dashboard/beneficiaries",
    "component": "C:\\\\Users\\\\acer\\\\Desktop\\\\allfiles\\\\palExchange\\\\frontend\\\\pages\\\\dashboard\\\\beneficiaries\\\\index.vue",
    "chunkName": "pages/dashboard/beneficiaries/index",
    "_name": "_0579105f"
  },
  {
    "name": "dashboard-exchange",
    "path": "/dashboard/exchange",
    "component": "C:\\\\Users\\\\acer\\\\Desktop\\\\allfiles\\\\palExchange\\\\frontend\\\\pages\\\\dashboard\\\\exchange\\\\index.vue",
    "chunkName": "pages/dashboard/exchange/index",
    "_name": "_c9aadb62"
  },
  {
    "name": "dashboard-inputs",
    "path": "/dashboard/inputs",
    "component": "C:\\\\Users\\\\acer\\\\Desktop\\\\allfiles\\\\palExchange\\\\frontend\\\\pages\\\\dashboard\\\\inputs\\\\index.vue",
    "chunkName": "pages/dashboard/inputs/index",
    "_name": "_3a7e7e6e"
  },
  {
    "name": "dashboard-inventory",
    "path": "/dashboard/inventory",
    "component": "C:\\\\Users\\\\acer\\\\Desktop\\\\allfiles\\\\palExchange\\\\frontend\\\\pages\\\\dashboard\\\\inventory\\\\index.vue",
    "chunkName": "pages/dashboard/inventory/index",
    "_name": "_0f7a2ba6"
  },
  {
    "name": "dashboard-moneygram",
    "path": "/dashboard/moneygram",
    "component": "C:\\\\Users\\\\acer\\\\Desktop\\\\allfiles\\\\palExchange\\\\frontend\\\\pages\\\\dashboard\\\\moneygram\\\\index.vue",
    "chunkName": "pages/dashboard/moneygram/index",
    "_name": "_2a61b1ea"
  },
  {
    "name": "dashboard-outputs",
    "path": "/dashboard/outputs",
    "component": "C:\\\\Users\\\\acer\\\\Desktop\\\\allfiles\\\\palExchange\\\\frontend\\\\pages\\\\dashboard\\\\outputs\\\\index.vue",
    "chunkName": "pages/dashboard/outputs/index",
    "_name": "_07d134a0"
  },
  {
    "name": "dashboard-profit",
    "path": "/dashboard/profit",
    "component": "C:\\\\Users\\\\acer\\\\Desktop\\\\allfiles\\\\palExchange\\\\frontend\\\\pages\\\\dashboard\\\\profit\\\\index.vue",
    "chunkName": "pages/dashboard/profit/index",
    "_name": "_603924e4"
  },
  {
    "name": "dashboard-reports",
    "path": "/dashboard/reports",
    "component": "C:\\\\Users\\\\acer\\\\Desktop\\\\allfiles\\\\palExchange\\\\frontend\\\\pages\\\\dashboard\\\\reports\\\\index.vue",
    "chunkName": "pages/dashboard/reports/index",
    "_name": "_8d1a253a"
  },
  {
    "name": "dashboard-settings",
    "path": "/dashboard/settings",
    "component": "C:\\\\Users\\\\acer\\\\Desktop\\\\allfiles\\\\palExchange\\\\frontend\\\\pages\\\\dashboard\\\\settings\\\\index.vue",
    "chunkName": "pages/dashboard/settings/index",
    "_name": "_6c58a44f"
  },
  {
    "name": "dashboard-transfers",
    "path": "/dashboard/transfers",
    "component": "C:\\\\Users\\\\acer\\\\Desktop\\\\allfiles\\\\palExchange\\\\frontend\\\\pages\\\\dashboard\\\\transfers\\\\index.vue",
    "chunkName": "pages/dashboard/transfers/index",
    "_name": "_6d1eef9a"
  },
  {
    "name": "dashboard-user-profit",
    "path": "/dashboard/user-profit",
    "component": "C:\\\\Users\\\\acer\\\\Desktop\\\\allfiles\\\\palExchange\\\\frontend\\\\pages\\\\dashboard\\\\user-profit\\\\index.vue",
    "chunkName": "pages/dashboard/user-profit/index",
    "_name": "_3f654e3c"
  },
  {
    "name": "dashboard-beneficiaries-form",
    "path": "/dashboard/beneficiaries/form",
    "component": "C:\\\\Users\\\\acer\\\\Desktop\\\\allfiles\\\\palExchange\\\\frontend\\\\pages\\\\dashboard\\\\beneficiaries\\\\form\\\\index.vue",
    "chunkName": "pages/dashboard/beneficiaries/form/index",
    "_name": "_2491f9db"
  },
  {
    "name": "dashboard-exchange-2",
    "path": "/dashboard/exchange/2",
    "component": "C:\\\\Users\\\\acer\\\\Desktop\\\\allfiles\\\\palExchange\\\\frontend\\\\pages\\\\dashboard\\\\exchange\\\\2.vue",
    "chunkName": "pages/dashboard/exchange/2",
    "_name": "_6a4a742f"
  },
  {
    "name": "dashboard-exchange-excel",
    "path": "/dashboard/exchange/excel",
    "component": "C:\\\\Users\\\\acer\\\\Desktop\\\\allfiles\\\\palExchange\\\\frontend\\\\pages\\\\dashboard\\\\exchange\\\\excel.vue",
    "chunkName": "pages/dashboard/exchange/excel",
    "_name": "_235541b4"
  },
  {
    "name": "dashboard-exchange-form",
    "path": "/dashboard/exchange/form",
    "component": "C:\\\\Users\\\\acer\\\\Desktop\\\\allfiles\\\\palExchange\\\\frontend\\\\pages\\\\dashboard\\\\exchange\\\\form\\\\index.vue",
    "chunkName": "pages/dashboard/exchange/form/index",
    "_name": "_e593706a"
  },
  {
    "name": "dashboard-exchange-multi",
    "path": "/dashboard/exchange/multi",
    "component": "C:\\\\Users\\\\acer\\\\Desktop\\\\allfiles\\\\palExchange\\\\frontend\\\\pages\\\\dashboard\\\\exchange\\\\multi.vue",
    "chunkName": "pages/dashboard/exchange/multi",
    "_name": "_f9489994"
  },
  {
    "name": "dashboard-exchange-test",
    "path": "/dashboard/exchange/test",
    "component": "C:\\\\Users\\\\acer\\\\Desktop\\\\allfiles\\\\palExchange\\\\frontend\\\\pages\\\\dashboard\\\\exchange\\\\test.vue",
    "chunkName": "pages/dashboard/exchange/test",
    "_name": "_4e86dda5"
  },
  {
    "name": "dashboard-inventory-form",
    "path": "/dashboard/inventory/form",
    "component": "C:\\\\Users\\\\acer\\\\Desktop\\\\allfiles\\\\palExchange\\\\frontend\\\\pages\\\\dashboard\\\\inventory\\\\form\\\\index.vue",
    "chunkName": "pages/dashboard/inventory/form/index",
    "_name": "_4425783c"
  },
  {
    "name": "dashboard-inventory-index2",
    "path": "/dashboard/inventory/index2",
    "component": "C:\\\\Users\\\\acer\\\\Desktop\\\\allfiles\\\\palExchange\\\\frontend\\\\pages\\\\dashboard\\\\inventory\\\\index2.vue",
    "chunkName": "pages/dashboard/inventory/index2",
    "_name": "_403a1b08"
  },
  {
    "name": "dashboard-reports-form",
    "path": "/dashboard/reports/form",
    "component": "C:\\\\Users\\\\acer\\\\Desktop\\\\allfiles\\\\palExchange\\\\frontend\\\\pages\\\\dashboard\\\\reports\\\\form\\\\index.vue",
    "chunkName": "pages/dashboard/reports/form/index",
    "_name": "_62e9f842"
  },
  {
    "name": "dashboard-settings-pricing",
    "path": "/dashboard/settings/pricing",
    "component": "C:\\\\Users\\\\acer\\\\Desktop\\\\allfiles\\\\palExchange\\\\frontend\\\\pages\\\\dashboard\\\\settings\\\\pricing.vue",
    "chunkName": "pages/dashboard/settings/pricing",
    "_name": "_04809c03"
  },
  {
    "name": "dashboard-settings-roles",
    "path": "/dashboard/settings/roles",
    "component": "C:\\\\Users\\\\acer\\\\Desktop\\\\allfiles\\\\palExchange\\\\frontend\\\\pages\\\\dashboard\\\\settings\\\\roles.vue",
    "chunkName": "pages/dashboard/settings/roles",
    "_name": "_9ce5c68c"
  },
  {
    "name": "dashboard-settings-settings",
    "path": "/dashboard/settings/settings",
    "component": "C:\\\\Users\\\\acer\\\\Desktop\\\\allfiles\\\\palExchange\\\\frontend\\\\pages\\\\dashboard\\\\settings\\\\settings.vue",
    "chunkName": "pages/dashboard/settings/settings",
    "_name": "_6e699d36"
  },
  {
    "name": "dashboard-settings-short-cuts",
    "path": "/dashboard/settings/short-cuts",
    "component": "C:\\\\Users\\\\acer\\\\Desktop\\\\allfiles\\\\palExchange\\\\frontend\\\\pages\\\\dashboard\\\\settings\\\\short-cuts.vue",
    "chunkName": "pages/dashboard/settings/short-cuts",
    "_name": "_10f707f5"
  },
  {
    "name": "dashboard-moneygram-incoming-temp_old",
    "path": "/dashboard/moneygram/incoming/temp_old",
    "component": "C:\\\\Users\\\\acer\\\\Desktop\\\\allfiles\\\\palExchange\\\\frontend\\\\pages\\\\dashboard\\\\moneygram\\\\incoming\\\\temp_old.vue",
    "chunkName": "pages/dashboard/moneygram/incoming/temp_old",
    "_name": "_47a89df9"
  },
  {
    "name": "dashboard-transfers-incoming-temp_old",
    "path": "/dashboard/transfers/incoming/temp_old",
    "component": "C:\\\\Users\\\\acer\\\\Desktop\\\\allfiles\\\\palExchange\\\\frontend\\\\pages\\\\dashboard\\\\transfers\\\\incoming\\\\temp_old.vue",
    "chunkName": "pages/dashboard/transfers/incoming/temp_old",
    "_name": "_a3bd146c"
  },
  {
    "name": "dashboard-beneficiaries-form-id",
    "path": "/dashboard/beneficiaries/form/:id",
    "component": "C:\\\\Users\\\\acer\\\\Desktop\\\\allfiles\\\\palExchange\\\\frontend\\\\pages\\\\dashboard\\\\beneficiaries\\\\form\\\\_id.vue",
    "chunkName": "pages/dashboard/beneficiaries/form/_id",
    "_name": "_287ab703"
  },
  {
    "name": "dashboard-exchange-form-id",
    "path": "/dashboard/exchange/form/:id",
    "component": "C:\\\\Users\\\\acer\\\\Desktop\\\\allfiles\\\\palExchange\\\\frontend\\\\pages\\\\dashboard\\\\exchange\\\\form\\\\_id.vue",
    "chunkName": "pages/dashboard/exchange/form/_id",
    "_name": "_b68c7e1a"
  },
  {
    "name": "dashboard-inputs-form-id",
    "path": "/dashboard/inputs/form/:id?",
    "component": "C:\\\\Users\\\\acer\\\\Desktop\\\\allfiles\\\\palExchange\\\\frontend\\\\pages\\\\dashboard\\\\inputs\\\\form\\\\_id.vue",
    "chunkName": "pages/dashboard/inputs/form/_id",
    "_name": "_7f7fbb26"
  },
  {
    "name": "dashboard-inventory-form-id",
    "path": "/dashboard/inventory/form/:id",
    "component": "C:\\\\Users\\\\acer\\\\Desktop\\\\allfiles\\\\palExchange\\\\frontend\\\\pages\\\\dashboard\\\\inventory\\\\form\\\\_id.vue",
    "chunkName": "pages/dashboard/inventory/form/_id",
    "_name": "_6b42526c"
  },
  {
    "name": "dashboard-moneygram-incoming-id",
    "path": "/dashboard/moneygram/incoming/:id?",
    "component": "C:\\\\Users\\\\acer\\\\Desktop\\\\allfiles\\\\palExchange\\\\frontend\\\\pages\\\\dashboard\\\\moneygram\\\\incoming\\\\_id.vue",
    "chunkName": "pages/dashboard/moneygram/incoming/_id",
    "_name": "_27533be6"
  },
  {
    "name": "dashboard-moneygram-outcoming-id",
    "path": "/dashboard/moneygram/outcoming/:id?",
    "component": "C:\\\\Users\\\\acer\\\\Desktop\\\\allfiles\\\\palExchange\\\\frontend\\\\pages\\\\dashboard\\\\moneygram\\\\outcoming\\\\_id.vue",
    "chunkName": "pages/dashboard/moneygram/outcoming/_id",
    "_name": "_433854bc"
  },
  {
    "name": "dashboard-outputs-form-id",
    "path": "/dashboard/outputs/form/:id?",
    "component": "C:\\\\Users\\\\acer\\\\Desktop\\\\allfiles\\\\palExchange\\\\frontend\\\\pages\\\\dashboard\\\\outputs\\\\form\\\\_id.vue",
    "chunkName": "pages/dashboard/outputs/form/_id",
    "_name": "_525bfbd4"
  },
  {
    "name": "dashboard-reports-form-id",
    "path": "/dashboard/reports/form/:id",
    "component": "C:\\\\Users\\\\acer\\\\Desktop\\\\allfiles\\\\palExchange\\\\frontend\\\\pages\\\\dashboard\\\\reports\\\\form\\\\_id.vue",
    "chunkName": "pages/dashboard/reports/form/_id",
    "_name": "_62767207"
  },
  {
    "name": "dashboard-transfers-incoming-id",
    "path": "/dashboard/transfers/incoming/:id?",
    "component": "C:\\\\Users\\\\acer\\\\Desktop\\\\allfiles\\\\palExchange\\\\frontend\\\\pages\\\\dashboard\\\\transfers\\\\incoming\\\\_id.vue",
    "chunkName": "pages/dashboard/transfers/incoming/_id",
    "_name": "_0ecfa8c8"
  },
  {
    "name": "dashboard-transfers-outcoming-id",
    "path": "/dashboard/transfers/outcoming/:id?",
    "component": "C:\\\\Users\\\\acer\\\\Desktop\\\\allfiles\\\\palExchange\\\\frontend\\\\pages\\\\dashboard\\\\transfers\\\\outcoming\\\\_id.vue",
    "chunkName": "pages/dashboard/transfers/outcoming/_id",
    "_name": "_5a5b3df3"
  },
  {
    "name": "index",
    "path": "/",
    "component": "C:\\\\Users\\\\acer\\\\Desktop\\\\allfiles\\\\palExchange\\\\frontend\\\\pages\\\\index.vue",
    "chunkName": "pages/index",
    "_name": "_bfd10424"
  }
]
